[
  {
    "name": "权力意志",
    "desc": "一切生命的本质是自我超越和增强的意志",
    "source": "查拉图斯特拉/善恶的彼岸"
  },
  {
    "name": "超人",
    "desc": "人是一种应当被超越的东西，价值的自我创造者",
    "source": "查拉图斯特拉如是说"
  },
  {
    "name": "永恒轮回",
    "desc": "如果生命无限重复，你是否能对每一刻说是",
    "source": "查拉图斯特拉/快乐的科学"
  },
  {
    "name": "上帝已死",
    "desc": "传统道德的形而上学基础崩塌，人必须自己创造价值",
    "source": "快乐的科学/查拉图斯特拉"
  },
  {
    "name": "主人道德vs奴隶道德",
    "desc": "主人道德来自自我肯定，奴隶道德来自怨恨",
    "source": "道德的谱系"
  },
  {
    "name": "酒神精神",
    "desc": "醉的狂欢、生命的肯定、混沌中的创造力",
    "source": "悲剧的诞生"
  },
  {
    "name": "日神精神",
    "desc": "梦的幻象、秩序、个体化原理、美的外观",
    "source": "悲剧的诞生"
  },
  {
    "name": "末人",
    "desc": "没有渴望、没有创造、只求安逸舒适的平庸之人",
    "source": "查拉图斯特拉如是说"
  },
  {
    "name": "深渊",
    "desc": "当你凝视深渊时深渊也在凝视你——自我认识的危险",
    "source": "善恶的彼岸"
  },
  {
    "name": "价值重估",
    "desc": "对所有传统价值进行彻底重新评估",
    "source": "偶像的黄昏/敌基督"
  },
  {
    "name": "爱命运(Amor Fati)",
    "desc": "热爱命运，不只是接受而是想要——对一切说是",
    "source": "瞧这个人/快乐的科学"
  },
  {
    "name": "精神三变",
    "desc": "骆驼->狮子->孩子：承担->反抗->创造新价值",
    "source": "查拉图斯特拉如是说"
  },
  {
    "name": "怨恨(Ressentiment)",
    "desc": "弱者的报复心理，把无力变成道德优越",
    "source": "道德的谱系"
  },
  {
    "name": "视角主义",
    "desc": "没有事实只有解释，一切认知都是特定视角的产物",
    "source": "遗稿"
  },
  {
    "name": "舞蹈的星辰",
    "desc": "你必须携带混沌才能生出舞蹈的星辰",
    "source": "查拉图斯特拉如是说"
  }
]